{
    "model_strategy_patterns": {
        "neutral": {
            "timestamp": "2026-03-09T12:52:53.040992",
            "model_confidences": {
                "Ridge": 1.0,
                "XGBoost": 1.0
            },
            "best_model": "Ridge"
        },
        "bull": {
            "timestamp": "2026-03-09T16:47:31.626905",
            "model_confidences": {
                "Ridge": 1.0,
                "XGBoost": 1.0
            },
            "best_model": "Ridge"
        },
        "bear": {
            "timestamp": "2026-03-09T12:53:08.326865",
            "model_confidences": {
                "Ridge": 1.0,
                "XGBoost": 1.0
            },
            "best_model": "Ridge"
        }
    }
}